LICENSE
MANIFEST.in
README.rst
setup.cfg
setup.py
versioneer.py
solstice/__init__.py
solstice/tools/__init__.py
solstice/tools/xgenmanager/__init__.py
solstice/tools/xgenmanager/__version__.py
solstice/tools/xgenmanager/_version.py
solstice/tools/xgenmanager/core/__init__.py
solstice/tools/xgenmanager/core/xgenmanager.py
solstice/tools/xgenmanager/resources/images/xgenmanager_logo.png
solstice/tools/xgenmanager/widgets/__init__.py
solstice/tools/xgenmanager/widgets/xgenmanager.py
solstice_tools_xgenmanager.egg-info/PKG-INFO
solstice_tools_xgenmanager.egg-info/SOURCES.txt
solstice_tools_xgenmanager.egg-info/dependency_links.txt
solstice_tools_xgenmanager.egg-info/not-zip-safe
solstice_tools_xgenmanager.egg-info/requires.txt
solstice_tools_xgenmanager.egg-info/top_level.txt
tests/__init__.py
tests/test_general.py