Metadata-Version: 2.1
Name: solstice-tools-xgenmanager
Version: 0.0.2
Summary: Tool to manage XGen workflow in Solstice
Home-page: https://github.com/Solstice-Short-Film/solstice-tools-xgenmanager
Author: Enrique Velasco
Author-email: enriquevelmai@hotmail.com
License: MIT
Platform: UNKNOWN
Provides-Extra: dev
Provides-Extra: test
